cookiecutter_autodocs/__init__.py
cookiecutter_autodocs/cli/__init__.py
cookiecutter_autodocs/cli/_async.py
cookiecutter_autodocs/cli/app.py
cookiecutter_autodocs/cli/generate.py
cookiecutter_autodocs/cli/gha.py
cookiecutter_autodocs/cli/validate.py
cookiecutter_autodocs/lib/__init__.py
cookiecutter_autodocs/lib/files.py
cookiecutter_autodocs/lib/typing.py
cookiecutter_autodocs/py.typed
cookiecutter_autodocs/schemas/__init__.py
cookiecutter_autodocs/schemas/_base.py
cookiecutter_autodocs/schemas/description.py
cookiecutter_autodocs-1.0.0.dist-info/LICENSE
cookiecutter_autodocs-1.0.0.dist-info/METADATA
cookiecutter_autodocs-1.0.0.dist-info/WHEEL
cookiecutter_autodocs-1.0.0.dist-info/entry_points.txt
cookiecutter_autodocs-1.0.0.dist-info/RECORD
