Metadata-Version: 2.1
Name: cookiecutter-autodocs
Version: 1.0.0
Summary: Generate docs from your cookiecutter template
License: MIT
Author: Andrew Herrington
Author-email: andrew.the.techie@gmail.com
Requires-Python: >=3.8,<4.0
Classifier: License :: OSI Approved :: MIT License
Classifier: Programming Language :: Python :: 3
Classifier: Programming Language :: Python :: 3.8
Classifier: Programming Language :: Python :: 3.9
Classifier: Programming Language :: Python :: 3.10
Classifier: Programming Language :: Python :: 3.11
Requires-Dist: aiofiles (>=23.1.0,<24.0.0)
Requires-Dist: py-markdown-table (>=0.3.3,<0.4.0)
Requires-Dist: pydantic (>=1.10.7,<2.0.0)
Requires-Dist: rich (>=13.3.4,<14.0.0)
Requires-Dist: toml (>=0.10.2,<0.11.0)
Requires-Dist: typer (>=0.7,<0.10)
